{
  "rustc_version": "1.92.0-nightly (a454fccb0 2025-09-15)",
  "rustc_host": "aarch64-unknown-linux-gnu",
  "project_root": ".",
  "expanded_files": [
    {
      "package_name": "autocfg",
      "target_type": "lib",
      "target_name": "autocfg",
      "expanded_rs_path": "expanded/.expand_output_autocfg_autocfg_lib.rs",
      "cargo_expand_command": "cargo expand --manifest-path /data/data/com.termux.nix/files/home/.cargo/registry/src/index.crates.io-1949cf8c6b5b557f/autocfg-1.5.0/Cargo.toml --lib --all-features --color=never --verbose",
      "timestamp": 1762429668,
      "flake_lock_details": {
        "nodes": {
          "allocator-api2": {
            "inputs": {
              "flake-utils": "flake-utils",
              "nixpkgs": "nixpkgs",
              "rust-overlay": "rust-overlay"
            },
            "locked": {
              "lastModified": 1760790639,
              "narHash": "sha256-tW7QACjn3B7HUN+Xm1jPLdZlpv2WmJgMSZCGAPuw9YM=",
              "owner": "meta-introspector",
              "repo": "allocator-api2",
              "rev": "291a618795755527fc2c8f9d7e678cecf0e238e5",
              "type": "github"
            },
            "original": {
              "owner": "meta-introspector",
              "ref": "feature/CRQ-016-nixify",
              "repo": "allocator-api2",
              "type": "github"
            }
          },
          "cargo2nix": {
            "inputs": {
              "allocator-api2": "allocator-api2",
              "context": "context",
              "flake-compat": "flake-compat",
              "flake-utils": "flake-utils_2",
              "nixpkgs": "nixpkgs_3",
              "rust-overlay": "rust-overlay_2"
            },
            "locked": {
              "lastModified": 1760808004,
              "narHash": "sha256-ByHnaj2K6dSx7BWDP8Txt+O2LA41Gb/mTLUjvxuFD2M=",
              "owner": "meta-introspector",
              "repo": "cargo2nix",
              "rev": "94d556e2ebf2125f3db581a6a5f870a2c85f2bbb",
              "type": "github"
            },
            "original": {
              "owner": "meta-introspector",
              "ref": "feature/CRQ-016-nixify",
              "repo": "cargo2nix",
              "type": "github"
            }
          },
          "context": {
            "flake": false,
            "locked": {
              "dir": "2025/10/10",
              "lastModified": 1759506839,
              "narHash": "sha256-TOH4TO9/97K0wC8wpv6mXw7eyKpGlZ0oenYfCkCr1J0=",
              "owner": "meta-introspector",
              "repo": "streamofrandom",
              "rev": "8f40e7de433d7c050d5bc2fe47f1f9eef819c886",
              "type": "github"
            },
            "original": {
              "dir": "2025/10/10",
              "owner": "meta-introspector",
              "ref": "feature/foaf",
              "repo": "streamofrandom",
              "type": "github"
            }
          },
          "flake-compat": {
            "flake": false,
            "locked": {
              "lastModified": 1746162366,
              "narHash": "sha256-5SSSZ/oQkwfcAz/o/6TlejlVGqeK08wyREBQ5qFFPhM=",
              "owner": "meta-introspector",
              "repo": "flake-compat",
              "rev": "0f158086a2ecdbb138cd0429410e44994f1b7e4b",
              "type": "github"
            },
            "original": {
              "owner": "meta-introspector",
              "ref": "feature/CRQ-016-nixify",
              "repo": "flake-compat",
              "type": "github"
            }
          },
          "flake-utils": {
            "inputs": {
              "systems": "systems"
            },
            "locked": {
              "lastModified": 1731533236,
              "narHash": "sha256-l0KFg5HjrsfsO/JpG+r7fRrqm12kzFHyUHqHCVpMMbI=",
              "owner": "meta-introspector",
              "repo": "flake-utils",
              "rev": "11707dc2f618dd54ca8739b309ec4fc024de578b",
              "type": "github"
            },
            "original": {
              "owner": "meta-introspector",
              "ref": "feature/CRQ-016-nixify",
              "repo": "flake-utils",
              "type": "github"
            }
          },
          "flake-utils_2": {
            "inputs": {
              "systems": "systems_2"
            },
            "locked": {
              "lastModified": 1731533236,
              "narHash": "sha256-l0KFg5HjrsfsO/JpG+r7fRrqm12kzFHyUHqHCVpMMbI=",
              "owner": "meta-introspector",
              "repo": "flake-utils",
              "rev": "11707dc2f618dd54ca8739b309ec4fc024de578b",
              "type": "github"
            },
            "original": {
              "owner": "meta-introspector",
              "ref": "feature/CRQ-016-nixify",
              "repo": "flake-utils",
              "type": "github"
            }
          },
          "flake-utils_3": {
            "inputs": {
              "systems": "systems_3"
            },
            "locked": {
              "lastModified": 1731533236,
              "narHash": "sha256-l0KFg5HjrsfsO/JpG+r7fRrqm12kzFHyUHqHCVpMMbI=",
              "owner": "meta-introspector",
              "repo": "flake-utils",
              "rev": "11707dc2f618dd54ca8739b309ec4fc024de578b",
              "type": "github"
            },
            "original": {
              "owner": "meta-introspector",
              "ref": "feature/CRQ-016-nixify",
              "repo": "flake-utils",
              "type": "github"
            }
          },
          "nixpkgs": {
            "locked": {
              "lastModified": 1757898380,
              "narHash": "sha256-1Z0KAfbySsHu/IoZbBJLrPgs3IqQGup0T8J9S1ffAkE=",
              "owner": "meta-introspector",
              "repo": "nixpkgs",
              "rev": "26833ad1dad83826ef7cc52e0009ca9b7097c79f",
              "type": "github"
            },
            "original": {
              "owner": "meta-introspector",
              "ref": "feature/CRQ-016-nixify",
              "repo": "nixpkgs",
              "type": "github"
            }
          },
          "nixpkgs_2": {
            "locked": {
              "lastModified": 1757898380,
              "narHash": "sha256-1Z0KAfbySsHu/IoZbBJLrPgs3IqQGup0T8J9S1ffAkE=",
              "owner": "meta-introspector",
              "repo": "nixpkgs",
              "rev": "26833ad1dad83826ef7cc52e0009ca9b7097c79f",
              "type": "github"
            },
            "original": {
              "owner": "meta-introspector",
              "ref": "feature/CRQ-016-nixify",
              "repo": "nixpkgs",
              "type": "github"
            }
          },
          "nixpkgs_3": {
            "locked": {
              "lastModified": 1757898380,
              "narHash": "sha256-1Z0KAfbySsHu/IoZbBJLrPgs3IqQGup0T8J9S1ffAkE=",
              "owner": "meta-introspector",
              "repo": "nixpkgs",
              "rev": "26833ad1dad83826ef7cc52e0009ca9b7097c79f",
              "type": "github"
            },
            "original": {
              "owner": "meta-introspector",
              "ref": "feature/CRQ-016-nixify",
              "repo": "nixpkgs",
              "type": "github"
            }
          },
          "nixpkgs_4": {
            "locked": {
              "lastModified": 1757898380,
              "narHash": "sha256-1Z0KAfbySsHu/IoZbBJLrPgs3IqQGup0T8J9S1ffAkE=",
              "owner": "meta-introspector",
              "repo": "nixpkgs",
              "rev": "26833ad1dad83826ef7cc52e0009ca9b7097c79f",
              "type": "github"
            },
            "original": {
              "owner": "meta-introspector",
              "ref": "feature/CRQ-016-nixify",
              "repo": "nixpkgs",
              "type": "github"
            }
          },
          "nixpkgs_5": {
            "locked": {
              "lastModified": 1757898380,
              "narHash": "sha256-1Z0KAfbySsHu/IoZbBJLrPgs3IqQGup0T8J9S1ffAkE=",
              "owner": "meta-introspector",
              "repo": "nixpkgs",
              "rev": "26833ad1dad83826ef7cc52e0009ca9b7097c79f",
              "type": "github"
            },
            "original": {
              "owner": "meta-introspector",
              "ref": "feature/CRQ-016-nixify",
              "repo": "nixpkgs",
              "type": "github"
            }
          },
          "nixpkgs_6": {
            "locked": {
              "lastModified": 1757898380,
              "narHash": "sha256-1Z0KAfbySsHu/IoZbBJLrPgs3IqQGup0T8J9S1ffAkE=",
              "owner": "meta-introspector",
              "repo": "nixpkgs",
              "rev": "26833ad1dad83826ef7cc52e0009ca9b7097c79f",
              "type": "github"
            },
            "original": {
              "owner": "meta-introspector",
              "ref": "feature/CRQ-016-nixify",
              "repo": "nixpkgs",
              "type": "github"
            }
          },
          "nixpkgs_7": {
            "locked": {
              "lastModified": 1757898380,
              "narHash": "sha256-1Z0KAfbySsHu/IoZbBJLrPgs3IqQGup0T8J9S1ffAkE=",
              "owner": "meta-introspector",
              "repo": "nixpkgs",
              "rev": "26833ad1dad83826ef7cc52e0009ca9b7097c79f",
              "type": "github"
            },
            "original": {
              "owner": "meta-introspector",
              "ref": "feature/CRQ-016-nixify",
              "repo": "nixpkgs",
              "type": "github"
            }
          },
          "root": {
            "inputs": {
              "cargo2nix": "cargo2nix",
              "nixpkgs": "nixpkgs_4",
              "rust-overlay": "rust-overlay_3",
              "rustSrcFlake": "rustSrcFlake"
            }
          },
          "rust-overlay": {
            "inputs": {
              "nixpkgs": "nixpkgs_2"
            },
            "locked": {
              "lastModified": 1760649444,
              "narHash": "sha256-K8OdikWA0y9JQxRgd+ZN7KzpS7Zsk/fdv6+WZMcNTOw=",
              "owner": "meta-introspector",
              "repo": "rust-overlay",
              "rev": "eee7767f08f58eb56822d7e85423098eb3e6dd65",
              "type": "github"
            },
            "original": {
              "owner": "meta-introspector",
              "ref": "feature/CRQ-016-nixify",
              "repo": "rust-overlay",
              "type": "github"
            }
          },
          "rust-overlay_2": {
            "inputs": {
              "nixpkgs": [
                "cargo2nix",
                "nixpkgs"
              ]
            },
            "locked": {
              "lastModified": 1759890791,
              "narHash": "sha256-KN1xkrQ4x6u8plgg43ZiYbQmESxeCKKOzALKjqbn4LM=",
              "owner": "meta-introspector",
              "repo": "rust-overlay",
              "rev": "74fcbc183aa6685f86008606bb7824bf2f40adbd",
              "type": "github"
            },
            "original": {
              "owner": "meta-introspector",
              "ref": "feature/CRQ-016-nixify",
              "repo": "rust-overlay",
              "type": "github"
            }
          },
          "rust-overlay_3": {
            "inputs": {
              "nixpkgs": "nixpkgs_5"
            },
            "locked": {
              "lastModified": 1760649444,
              "narHash": "sha256-K8OdikWA0y9JQxRgd+ZN7KzpS7Zsk/fdv6+WZMcNTOw=",
              "owner": "meta-introspector",
              "repo": "rust-overlay",
              "rev": "eee7767f08f58eb56822d7e85423098eb3e6dd65",
              "type": "github"
            },
            "original": {
              "owner": "meta-introspector",
              "ref": "feature/CRQ-016-nixify",
              "repo": "rust-overlay",
              "type": "github"
            }
          },
          "rust-overlay_4": {
            "inputs": {
              "nixpkgs": "nixpkgs_7"
            },
            "locked": {
              "lastModified": 1760649444,
              "narHash": "sha256-K8OdikWA0y9JQxRgd+ZN7KzpS7Zsk/fdv6+WZMcNTOw=",
              "owner": "meta-introspector",
              "repo": "rust-overlay",
              "rev": "eee7767f08f58eb56822d7e85423098eb3e6dd65",
              "type": "github"
            },
            "original": {
              "owner": "meta-introspector",
              "ref": "feature/CRQ-016-nixify",
              "repo": "rust-overlay",
              "type": "github"
            }
          },
          "rustSrcFlake": {
            "inputs": {
              "flake-utils": "flake-utils_3",
              "nixpkgs": "nixpkgs_6",
              "rust-overlay": "rust-overlay_4"
            },
            "locked": {
              "lastModified": 1760870238,
              "narHash": "sha256-TGYIcYZLXedd4M3LNhqpKHMScQcwo7YOjIWhMmY4tvE=",
              "owner": "meta-introspector",
              "repo": "rust",
              "rev": "3487cd3843083db70ee30023f19344568ade9c9f",
              "type": "github"
            },
            "original": {
              "owner": "meta-introspector",
              "ref": "feature/CRQ-016-nixify",
              "repo": "rust",
              "type": "github"
            }
          },
          "systems": {
            "locked": {
              "lastModified": 1681028828,
              "narHash": "sha256-Vy1rq5AaRuLzOxct8nz4T6wlgyUR7zLU309k9mBC768=",
              "owner": "nix-systems",
              "repo": "default",
              "rev": "da67096a3b9bf56a91d16901293e51ba5b49a27e",
              "type": "github"
            },
            "original": {
              "owner": "nix-systems",
              "repo": "default",
              "type": "github"
            }
          },
          "systems_2": {
            "locked": {
              "lastModified": 1681028828,
              "narHash": "sha256-Vy1rq5AaRuLzOxct8nz4T6wlgyUR7zLU309k9mBC768=",
              "owner": "nix-systems",
              "repo": "default",
              "rev": "da67096a3b9bf56a91d16901293e51ba5b49a27e",
              "type": "github"
            },
            "original": {
              "owner": "nix-systems",
              "repo": "default",
              "type": "github"
            }
          },
          "systems_3": {
            "locked": {
              "lastModified": 1681028828,
              "narHash": "sha256-Vy1rq5AaRuLzOxct8nz4T6wlgyUR7zLU309k9mBC768=",
              "owner": "nix-systems",
              "repo": "default",
              "rev": "da67096a3b9bf56a91d16901293e51ba5b49a27e",
              "type": "github"
            },
            "original": {
              "owner": "nix-systems",
              "repo": "default",
              "type": "github"
            }
          }
        },
        "root": "root",
        "version": 7
      },
      "layer": 0,
      "file_size": 36354,
      "declaration_counts": {
        "Use": 13,
        "Other": 1,
        "Impl": 3,
        "Struct": 1,
        "Function": 9,
        "Module": 3
      },
      "type_usages": {
        "& Version": {
          "type_name": "& Version",
          "function_count": 0,
          "struct_count": 0,
          "enum_count": 0,
          "trait_count": 0,
          "module_count": 3,
          "constant_count": 0,
          "static_count": 0,
          "macro_count": 0,
          "use_count": 0,
          "impl_count": 0,
          "foreign_mod_count": 0,
          "type_alias_count": 0,
          "other_count": 0
        },
        "& mut Command": {
          "type_name": "& mut Command",
          "function_count": 0,
          "struct_count": 0,
          "enum_count": 0,
          "trait_count": 0,
          "module_count": 1,
          "constant_count": 0,
          "static_count": 0,
          "macro_count": 0,
          "use_count": 0,
          "impl_count": 0,
          "foreign_mod_count": 0,
          "type_alias_count": 0,
          "other_count": 0
        },
        "AtomicUsize": {
          "type_name": "AtomicUsize",
          "function_count": 0,
          "struct_count": 0,
          "enum_count": 0,
          "trait_count": 0,
          "module_count": 0,
          "constant_count": 0,
          "static_count": 0,
          "macro_count": 0,
          "use_count": 0,
          "impl_count": 1,
          "foreign_mod_count": 0,
          "type_alias_count": 0,
          "other_count": 0
        },
        "Vec < String >": {
          "type_name": "Vec < String >",
          "function_count": 1,
          "struct_count": 1,
          "enum_count": 0,
          "trait_count": 0,
          "module_count": 0,
          "constant_count": 0,
          "static_count": 0,
          "macro_count": 0,
          "use_count": 0,
          "impl_count": 0,
          "foreign_mod_count": 0,
          "type_alias_count": 0,
          "other_count": 0
        },
        "Command": {
          "type_name": "Command",
          "function_count": 0,
          "struct_count": 0,
          "enum_count": 0,
          "trait_count": 0,
          "module_count": 2,
          "constant_count": 0,
          "static_count": 0,
          "macro_count": 0,
          "use_count": 0,
          "impl_count": 0,
          "foreign_mod_count": 0,
          "type_alias_count": 0,
          "other_count": 0
        },
        "& 'static str": {
          "type_name": "& 'static str",
          "function_count": 0,
          "struct_count": 0,
          "enum_count": 0,
          "trait_count": 0,
          "module_count": 2,
          "constant_count": 0,
          "static_count": 0,
          "macro_count": 0,
          "use_count": 0,
          "impl_count": 0,
          "foreign_mod_count": 0,
          "type_alias_count": 0,
          "other_count": 0
        },
        "& str": {
          "type_name": "& str",
          "function_count": 5,
          "struct_count": 0,
          "enum_count": 0,
          "trait_count": 0,
          "module_count": 1,
          "constant_count": 0,
          "static_count": 0,
          "macro_count": 0,
          "use_count": 0,
          "impl_count": 22,
          "foreign_mod_count": 0,
          "type_alias_count": 0,
          "other_count": 0
        },
        "T": {
          "type_name": "T",
          "function_count": 0,
          "struct_count": 0,
          "enum_count": 0,
          "trait_count": 0,
          "module_count": 0,
          "constant_count": 0,
          "static_count": 0,
          "macro_count": 0,
          "use_count": 0,
          "impl_count": 1,
          "foreign_mod_count": 0,
          "type_alias_count": 0,
          "other_count": 0
        },
        "& error :: Error": {
          "type_name": "& error :: Error",
          "function_count": 0,
          "struct_count": 0,
          "enum_count": 0,
          "trait_count": 0,
          "module_count": 1,
          "constant_count": 0,
          "static_count": 0,
          "macro_count": 0,
          "use_count": 0,
          "impl_count": 0,
          "foreign_mod_count": 0,
          "type_alias_count": 0,
          "other_count": 0
        },
        "Result < () , fmt :: Error >": {
          "type_name": "Result < () , fmt :: Error >",
          "function_count": 0,
          "struct_count": 0,
          "enum_count": 0,
          "trait_count": 0,
          "module_count": 1,
          "constant_count": 0,
          "static_count": 0,
          "macro_count": 0,
          "use_count": 0,
          "impl_count": 0,
          "foreign_mod_count": 0,
          "type_alias_count": 0,
          "other_count": 0
        },
        "fmt :: Formatter": {
          "type_name": "fmt :: Formatter",
          "function_count": 0,
          "struct_count": 0,
          "enum_count": 0,
          "trait_count": 0,
          "module_count": 1,
          "constant_count": 0,
          "static_count": 0,
          "macro_count": 0,
          "use_count": 0,
          "impl_count": 0,
          "foreign_mod_count": 0,
          "type_alias_count": 0,
          "other_count": 0
        },
        "Error": {
          "type_name": "Error",
          "function_count": 0,
          "struct_count": 0,
          "enum_count": 0,
          "trait_count": 0,
          "module_count": 10,
          "constant_count": 0,
          "static_count": 0,
          "macro_count": 0,
          "use_count": 0,
          "impl_count": 4,
          "foreign_mod_count": 0,
          "type_alias_count": 0,
          "other_count": 0
        },
        "& mut fmt :: Formatter": {
          "type_name": "& mut fmt :: Formatter",
          "function_count": 0,
          "struct_count": 0,
          "enum_count": 0,
          "trait_count": 0,
          "module_count": 1,
          "constant_count": 0,
          "static_count": 0,
          "macro_count": 0,
          "use_count": 0,
          "impl_count": 0,
          "foreign_mod_count": 0,
          "type_alias_count": 0,
          "other_count": 0
        },
        "Result < () , Error >": {
          "type_name": "Result < () , Error >",
          "function_count": 0,
          "struct_count": 0,
          "enum_count": 0,
          "trait_count": 0,
          "module_count": 0,
          "constant_count": 0,
          "static_count": 0,
          "macro_count": 0,
          "use_count": 0,
          "impl_count": 2,
          "foreign_mod_count": 0,
          "type_alias_count": 0,
          "other_count": 0
        },
        "fmt :: Error": {
          "type_name": "fmt :: Error",
          "function_count": 0,
          "struct_count": 0,
          "enum_count": 0,
          "trait_count": 0,
          "module_count": 1,
          "constant_count": 0,
          "static_count": 0,
          "macro_count": 0,
          "use_count": 0,
          "impl_count": 0,
          "foreign_mod_count": 0,
          "type_alias_count": 0,
          "other_count": 0
        },
        "Result < Version , Error >": {
          "type_name": "Result < Version , Error >",
          "function_count": 0,
          "struct_count": 0,
          "enum_count": 0,
          "trait_count": 0,
          "module_count": 1,
          "constant_count": 0,
          "static_count": 0,
          "macro_count": 0,
          "use_count": 0,
          "impl_count": 0,
          "foreign_mod_count": 0,
          "type_alias_count": 0,
          "other_count": 0
        },
        ":: core :: option :: Option < :: core :: cmp :: Ordering >": {
          "type_name": ":: core :: option :: Option < :: core :: cmp :: Ordering >",
          "function_count": 0,
          "struct_count": 0,
          "enum_count": 0,
          "trait_count": 0,
          "module_count": 1,
          "constant_count": 0,
          "static_count": 0,
          "macro_count": 0,
          "use_count": 0,
          "impl_count": 0,
          "foreign_mod_count": 0,
          "type_alias_count": 0,
          "other_count": 0
        },
        "Option < String >": {
          "type_name": "Option < String >",
          "function_count": 0,
          "struct_count": 1,
          "enum_count": 0,
          "trait_count": 0,
          "module_count": 0,
          "constant_count": 0,
          "static_count": 0,
          "macro_count": 0,
          "use_count": 0,
          "impl_count": 1,
          "foreign_mod_count": 0,
          "type_alias_count": 0,
          "other_count": 0
        },
        "usize": {
          "type_name": "usize",
          "function_count": 0,
          "struct_count": 0,
          "enum_count": 0,
          "trait_count": 0,
          "module_count": 7,
          "constant_count": 0,
          "static_count": 0,
          "macro_count": 0,
          "use_count": 0,
          "impl_count": 4,
          "foreign_mod_count": 0,
          "type_alias_count": 0,
          "other_count": 0
        },
        "error :: Error": {
          "type_name": "error :: Error",
          "function_count": 0,
          "struct_count": 0,
          "enum_count": 0,
          "trait_count": 0,
          "module_count": 1,
          "constant_count": 0,
          "static_count": 0,
          "macro_count": 0,
          "use_count": 0,
          "impl_count": 0,
          "foreign_mod_count": 0,
          "type_alias_count": 0,
          "other_count": 0
        },
        "Arguments < 'a >": {
          "type_name": "Arguments < 'a >",
          "function_count": 0,
          "struct_count": 0,
          "enum_count": 0,
          "trait_count": 0,
          "module_count": 0,
          "constant_count": 0,
          "static_count": 0,
          "macro_count": 0,
          "use_count": 0,
          "impl_count": 2,
          "foreign_mod_count": 0,
          "type_alias_count": 0,
          "other_count": 0
        },
        "process :: ExitStatus": {
          "type_name": "process :: ExitStatus",
          "function_count": 0,
          "struct_count": 0,
          "enum_count": 0,
          "trait_count": 0,
          "module_count": 2,
          "constant_count": 0,
          "static_count": 0,
          "macro_count": 0,
          "use_count": 0,
          "impl_count": 0,
          "foreign_mod_count": 0,
          "type_alias_count": 0,
          "other_count": 0
        },
        "std :: collections :: HashSet < u64 >": {
          "type_name": "std :: collections :: HashSet < u64 >",
          "function_count": 1,
          "struct_count": 0,
          "enum_count": 0,
          "trait_count": 0,
          "module_count": 0,
          "constant_count": 0,
          "static_count": 0,
          "macro_count": 0,
          "use_count": 0,
          "impl_count": 0,
          "foreign_mod_count": 0,
          "type_alias_count": 0,
          "other_count": 0
        },
        ":: core :: cmp :: AssertParamIsEq < usize >": {
          "type_name": ":: core :: cmp :: AssertParamIsEq < usize >",
          "function_count": 0,
          "struct_count": 0,
          "enum_count": 0,
          "trait_count": 0,
          "module_count": 1,
          "constant_count": 0,
          "static_count": 0,
          "macro_count": 0,
          "use_count": 0,
          "impl_count": 0,
          "foreign_mod_count": 0,
          "type_alias_count": 0,
          "other_count": 0
        },
        "ErrorKind": {
          "type_name": "ErrorKind",
          "function_count": 0,
          "struct_count": 0,
          "enum_count": 0,
          "trait_count": 0,
          "module_count": 2,
          "constant_count": 0,
          "static_count": 0,
          "macro_count": 0,
          "use_count": 0,
          "impl_count": 0,
          "foreign_mod_count": 0,
          "type_alias_count": 0,
          "other_count": 0
        },
        "& mut :: core :: fmt :: Formatter": {
          "type_name": "& mut :: core :: fmt :: Formatter",
          "function_count": 0,
          "struct_count": 0,
          "enum_count": 0,
          "trait_count": 0,
          "module_count": 4,
          "constant_count": 0,
          "static_count": 0,
          "macro_count": 0,
          "use_count": 0,
          "impl_count": 1,
          "foreign_mod_count": 0,
          "type_alias_count": 0,
          "other_count": 0
        },
        "u64": {
          "type_name": "u64",
          "function_count": 5,
          "struct_count": 1,
          "enum_count": 0,
          "trait_count": 0,
          "module_count": 0,
          "constant_count": 0,
          "static_count": 0,
          "macro_count": 0,
          "use_count": 0,
          "impl_count": 0,
          "foreign_mod_count": 0,
          "type_alias_count": 0,
          "other_count": 0
        },
        "Option < & str >": {
          "type_name": "Option < & str >",
          "function_count": 0,
          "struct_count": 0,
          "enum_count": 0,
          "trait_count": 0,
          "module_count": 0,
          "constant_count": 0,
          "static_count": 0,
          "macro_count": 0,
          "use_count": 0,
          "impl_count": 1,
          "foreign_mod_count": 0,
          "type_alias_count": 0,
          "other_count": 0
        },
        "_": {
          "type_name": "_",
          "function_count": 0,
          "struct_count": 0,
          "enum_count": 0,
          "trait_count": 0,
          "module_count": 0,
          "constant_count": 0,
          "static_count": 0,
          "macro_count": 0,
          "use_count": 0,
          "impl_count": 1,
          "foreign_mod_count": 0,
          "type_alias_count": 0,
          "other_count": 0
        },
        ":: core :: fmt :: Formatter": {
          "type_name": ":: core :: fmt :: Formatter",
          "function_count": 0,
          "struct_count": 0,
          "enum_count": 0,
          "trait_count": 0,
          "module_count": 4,
          "constant_count": 0,
          "static_count": 0,
          "macro_count": 0,
          "use_count": 0,
          "impl_count": 1,
          "foreign_mod_count": 0,
          "type_alias_count": 0,
          "other_count": 0
        },
        "& Path": {
          "type_name": "& Path",
          "function_count": 2,
          "struct_count": 0,
          "enum_count": 0,
          "trait_count": 0,
          "module_count": 0,
          "constant_count": 0,
          "static_count": 0,
          "macro_count": 0,
          "use_count": 0,
          "impl_count": 0,
          "foreign_mod_count": 0,
          "type_alias_count": 0,
          "other_count": 0
        },
        "io :: Error": {
          "type_name": "io :: Error",
          "function_count": 0,
          "struct_count": 0,
          "enum_count": 0,
          "trait_count": 0,
          "module_count": 2,
          "constant_count": 0,
          "static_count": 0,
          "macro_count": 0,
          "use_count": 0,
          "impl_count": 0,
          "foreign_mod_count": 0,
          "type_alias_count": 0,
          "other_count": 0
        },
        "& Self": {
          "type_name": "& Self",
          "function_count": 0,
          "struct_count": 0,
          "enum_count": 0,
          "trait_count": 0,
          "module_count": 15,
          "constant_count": 0,
          "static_count": 0,
          "macro_count": 0,
          "use_count": 0,
          "impl_count": 25,
          "foreign_mod_count": 0,
          "type_alias_count": 0,
          "other_count": 0
        },
        "OsString": {
          "type_name": "OsString",
          "function_count": 3,
          "struct_count": 1,
          "enum_count": 0,
          "trait_count": 0,
          "module_count": 0,
          "constant_count": 0,
          "static_count": 0,
          "macro_count": 0,
          "use_count": 0,
          "impl_count": 0,
          "foreign_mod_count": 0,
          "type_alias_count": 0,
          "other_count": 0
        },
        "Option < PathBuf >": {
          "type_name": "Option < PathBuf >",
          "function_count": 0,
          "struct_count": 0,
          "enum_count": 0,
          "trait_count": 0,
          "module_count": 3,
          "constant_count": 0,
          "static_count": 0,
          "macro_count": 0,
          "use_count": 0,
          "impl_count": 0,
          "foreign_mod_count": 0,
          "type_alias_count": 0,
          "other_count": 0
        },
        "()": {
          "type_name": "()",
          "function_count": 0,
          "struct_count": 0,
          "enum_count": 0,
          "trait_count": 0,
          "module_count": 2,
          "constant_count": 0,
          "static_count": 0,
          "macro_count": 0,
          "use_count": 0,
          "impl_count": 2,
          "foreign_mod_count": 0,
          "type_alias_count": 0,
          "other_count": 0
        },
        "Option < OsString >": {
          "type_name": "Option < OsString >",
          "function_count": 3,
          "struct_count": 1,
          "enum_count": 0,
          "trait_count": 0,
          "module_count": 0,
          "constant_count": 0,
          "static_count": 0,
          "macro_count": 0,
          "use_count": 0,
          "impl_count": 0,
          "foreign_mod_count": 0,
          "type_alias_count": 0,
          "other_count": 0
        },
        "& [& dyn :: core :: fmt :: Debug]": {
          "type_name": "& [& dyn :: core :: fmt :: Debug]",
          "function_count": 0,
          "struct_count": 0,
          "enum_count": 0,
          "trait_count": 0,
          "module_count": 0,
          "constant_count": 0,
          "static_count": 0,
          "macro_count": 0,
          "use_count": 0,
          "impl_count": 1,
          "foreign_mod_count": 0,
          "type_alias_count": 0,
          "other_count": 0
        },
        "str": {
          "type_name": "str",
          "function_count": 5,
          "struct_count": 0,
          "enum_count": 0,
          "trait_count": 0,
          "module_count": 3,
          "constant_count": 0,
          "static_count": 0,
          "macro_count": 0,
          "use_count": 0,
          "impl_count": 22,
          "foreign_mod_count": 0,
          "type_alias_count": 0,
          "other_count": 0
        },
        "dyn :: core :: fmt :: Debug": {
          "type_name": "dyn :: core :: fmt :: Debug",
          "function_count": 0,
          "struct_count": 0,
          "enum_count": 0,
          "trait_count": 0,
          "module_count": 0,
          "constant_count": 0,
          "static_count": 0,
          "macro_count": 0,
          "use_count": 0,
          "impl_count": 1,
          "foreign_mod_count": 0,
          "type_alias_count": 0,
          "other_count": 0
        },
        "Option < & error :: Error >": {
          "type_name": "Option < & error :: Error >",
          "function_count": 0,
          "struct_count": 0,
          "enum_count": 0,
          "trait_count": 0,
          "module_count": 1,
          "constant_count": 0,
          "static_count": 0,
          "macro_count": 0,
          "use_count": 0,
          "impl_count": 0,
          "foreign_mod_count": 0,
          "type_alias_count": 0,
          "other_count": 0
        },
        "& mut Self": {
          "type_name": "& mut Self",
          "function_count": 0,
          "struct_count": 0,
          "enum_count": 0,
          "trait_count": 0,
          "module_count": 0,
          "constant_count": 0,
          "static_count": 0,
          "macro_count": 0,
          "use_count": 0,
          "impl_count": 2,
          "foreign_mod_count": 0,
          "type_alias_count": 0,
          "other_count": 0
        },
        ":: core :: cmp :: Ordering": {
          "type_name": ":: core :: cmp :: Ordering",
          "function_count": 0,
          "struct_count": 0,
          "enum_count": 0,
          "trait_count": 0,
          "module_count": 2,
          "constant_count": 0,
          "static_count": 0,
          "macro_count": 0,
          "use_count": 0,
          "impl_count": 0,
          "foreign_mod_count": 0,
          "type_alias_count": 0,
          "other_count": 0
        },
        "AutoCfg": {
          "type_name": "AutoCfg",
          "function_count": 1,
          "struct_count": 0,
          "enum_count": 0,
          "trait_count": 0,
          "module_count": 0,
          "constant_count": 0,
          "static_count": 0,
          "macro_count": 0,
          "use_count": 0,
          "impl_count": 4,
          "foreign_mod_count": 0,
          "type_alias_count": 0,
          "other_count": 0
        },
        "num :: ParseIntError": {
          "type_name": "num :: ParseIntError",
          "function_count": 0,
          "struct_count": 0,
          "enum_count": 0,
          "trait_count": 0,
          "module_count": 2,
          "constant_count": 0,
          "static_count": 0,
          "macro_count": 0,
          "use_count": 0,
          "impl_count": 0,
          "foreign_mod_count": 0,
          "type_alias_count": 0,
          "other_count": 0
        },
        "str :: Utf8Error": {
          "type_name": "str :: Utf8Error",
          "function_count": 0,
          "struct_count": 0,
          "enum_count": 0,
          "trait_count": 0,
          "module_count": 2,
          "constant_count": 0,
          "static_count": 0,
          "macro_count": 0,
          "use_count": 0,
          "impl_count": 0,
          "foreign_mod_count": 0,
          "type_alias_count": 0,
          "other_count": 0
        },
        "& Option < OsString >": {
          "type_name": "& Option < OsString >",
          "function_count": 2,
          "struct_count": 0,
          "enum_count": 0,
          "trait_count": 0,
          "module_count": 0,
          "constant_count": 0,
          "static_count": 0,
          "macro_count": 0,
          "use_count": 0,
          "impl_count": 0,
          "foreign_mod_count": 0,
          "type_alias_count": 0,
          "other_count": 0
        },
        "Result < Self , Error >": {
          "type_name": "Result < Self , Error >",
          "function_count": 0,
          "struct_count": 0,
          "enum_count": 0,
          "trait_count": 0,
          "module_count": 1,
          "constant_count": 0,
          "static_count": 0,
          "macro_count": 0,
          "use_count": 0,
          "impl_count": 2,
          "foreign_mod_count": 0,
          "type_alias_count": 0,
          "other_count": 0
        },
        "PathBuf": {
          "type_name": "PathBuf",
          "function_count": 0,
          "struct_count": 1,
          "enum_count": 0,
          "trait_count": 0,
          "module_count": 4,
          "constant_count": 0,
          "static_count": 0,
          "macro_count": 0,
          "use_count": 0,
          "impl_count": 1,
          "foreign_mod_count": 0,
          "type_alias_count": 0,
          "other_count": 0
        },
        "Self": {
          "type_name": "Self",
          "function_count": 0,
          "struct_count": 0,
          "enum_count": 0,
          "trait_count": 0,
          "module_count": 18,
          "constant_count": 0,
          "static_count": 0,
          "macro_count": 0,
          "use_count": 0,
          "impl_count": 29,
          "foreign_mod_count": 0,
          "type_alias_count": 0,
          "other_count": 0
        },
        "Version": {
          "type_name": "Version",
          "function_count": 0,
          "struct_count": 1,
          "enum_count": 0,
          "trait_count": 0,
          "module_count": 13,
          "constant_count": 0,
          "static_count": 0,
          "macro_count": 0,
          "use_count": 0,
          "impl_count": 0,
          "foreign_mod_count": 0,
          "type_alias_count": 0,
          "other_count": 0
        },
        "& dyn :: core :: fmt :: Debug": {
          "type_name": "& dyn :: core :: fmt :: Debug",
          "function_count": 0,
          "struct_count": 0,
          "enum_count": 0,
          "trait_count": 0,
          "module_count": 0,
          "constant_count": 0,
          "static_count": 0,
          "macro_count": 0,
          "use_count": 0,
          "impl_count": 1,
          "foreign_mod_count": 0,
          "type_alias_count": 0,
          "other_count": 0
        },
        "Rustc": {
          "type_name": "Rustc",
          "function_count": 0,
          "struct_count": 1,
          "enum_count": 0,
          "trait_count": 0,
          "module_count": 4,
          "constant_count": 0,
          "static_count": 0,
          "macro_count": 0,
          "use_count": 0,
          "impl_count": 0,
          "foreign_mod_count": 0,
          "type_alias_count": 0,
          "other_count": 0
        },
        "Path": {
          "type_name": "Path",
          "function_count": 2,
          "struct_count": 0,
          "enum_count": 0,
          "trait_count": 0,
          "module_count": 0,
          "constant_count": 0,
          "static_count": 0,
          "macro_count": 0,
          "use_count": 0,
          "impl_count": 0,
          "foreign_mod_count": 0,
          "type_alias_count": 0,
          "other_count": 0
        },
        ":: core :: fmt :: Result": {
          "type_name": ":: core :: fmt :: Result",
          "function_count": 0,
          "struct_count": 0,
          "enum_count": 0,
          "trait_count": 0,
          "module_count": 4,
          "constant_count": 0,
          "static_count": 0,
          "macro_count": 0,
          "use_count": 0,
          "impl_count": 1,
          "foreign_mod_count": 0,
          "type_alias_count": 0,
          "other_count": 0
        },
        "bool": {
          "type_name": "bool",
          "function_count": 1,
          "struct_count": 1,
          "enum_count": 0,
          "trait_count": 0,
          "module_count": 2,
          "constant_count": 0,
          "static_count": 0,
          "macro_count": 0,
          "use_count": 0,
          "impl_count": 10,
          "foreign_mod_count": 0,
          "type_alias_count": 0,
          "other_count": 0
        },
        "[& dyn :: core :: fmt :: Debug]": {
          "type_name": "[& dyn :: core :: fmt :: Debug]",
          "function_count": 0,
          "struct_count": 0,
          "enum_count": 0,
          "trait_count": 0,
          "module_count": 0,
          "constant_count": 0,
          "static_count": 0,
          "macro_count": 0,
          "use_count": 0,
          "impl_count": 1,
          "foreign_mod_count": 0,
          "type_alias_count": 0,
          "other_count": 0
        },
        "& 'static _": {
          "type_name": "& 'static _",
          "function_count": 0,
          "struct_count": 0,
          "enum_count": 0,
          "trait_count": 0,
          "module_count": 0,
          "constant_count": 0,
          "static_count": 0,
          "macro_count": 0,
          "use_count": 0,
          "impl_count": 1,
          "foreign_mod_count": 0,
          "type_alias_count": 0,
          "other_count": 0
        },
        "String": {
          "type_name": "String",
          "function_count": 2,
          "struct_count": 2,
          "enum_count": 0,
          "trait_count": 0,
          "module_count": 0,
          "constant_count": 0,
          "static_count": 0,
          "macro_count": 0,
          "use_count": 0,
          "impl_count": 2,
          "foreign_mod_count": 0,
          "type_alias_count": 0,
          "other_count": 0
        }
      }
    }
  ]
}